<!--

This file defines garrisons in game.

Fields index:
	Sector  		- it is where garrison will be sitting. Provide valid sector name.

	Composition		- it is composition index of garrison. Composition define quantity
				  and quality of enemy forces. Look into ArmyCompositions.xml for
				  more information.

NOTE: Maximum 100 garrisons can be used in game.

Changes require starting of a new game.

-->
<GARRISON_INFO>
   <GARRISON>
      <!--#1-->
      <!--Atremo-->
      <Sector>A9</Sector>
      <Composition>10</Composition>
   </GARRISON>
   <GARRISON>
      <!--#2-->
      <!--Atremo-->
      <Sector>A10</Sector>
      <Composition>10</Composition>
   </GARRISON>
   <GARRISON>
      <!--#3-->
      <!--Excess Atremo - K11-->
      <Sector>K11</Sector>
      <Composition>10</Composition>
   </GARRISON>
   <GARRISON>
      <!--#4-->
      <!--Excess Atremo - N9-->
      <Sector>N9</Sector>
      <Composition>10</Composition>
   </GARRISON>
   <GARRISON>
      <!--#5-->
      <!--Sheraton-->
      <Sector>A2</Sector>
      <Composition>7</Composition>
   </GARRISON>
   <GARRISON>
      <!--#6-->
      <!--Sheraton-->
      <Sector>B1</Sector>
      <Composition>8</Composition>
   </GARRISON>
   <GARRISON>
      <!--#7-->
      <!--Sheraton-->
      <Sector>B2</Sector>
      <Composition>9</Composition>
   </GARRISON>
   <GARRISON>
      <!--#8-->
      <!--Port Kip-->
      <Sector>C4</Sector>
      <Composition>8</Composition>
   </GARRISON>
   <GARRISON>
      <!--#9-->
      <!--Port Kip-->
      <Sector>C5</Sector>
      <Composition>8</Composition>
   </GARRISON>
   <GARRISON>
      <!--#10-->
      <!--Port Kip-->
      <Sector>C6</Sector>
      <Composition>8</Composition>
   </GARRISON>
   <GARRISON>
      <!--#11-->
      <!--Port Kip-->
      <Sector>D4</Sector>
      <Composition>8</Composition>
   </GARRISON>
   <GARRISON>
      <!--#12-->
      <!--Port Kip-->
      <Sector>D5</Sector>
      <Composition>8</Composition>
   </GARRISON>
   <GARRISON>
      <!--#13-->
      <!--Port Kip-->
      <Sector>D6</Sector>
      <Composition>8</Composition>
   </GARRISON>
   <GARRISON>
      <!--#14-->
      <!--Port Kip-->
      <Sector>D7</Sector>
      <Composition>8</Composition>
   </GARRISON>
   <GARRISON>
      <!--#15-->
      <!--Calisto-->
      <Sector>B13</Sector>
      <Composition>6</Composition>
   </GARRISON>
   <GARRISON>
      <!--#16-->
      <!--Calisto-->
      <Sector>B14</Sector>
      <Composition>6</Composition>
   </GARRISON>
   <GARRISON>
      <!--#17-->
      <!--Calisto-->
      <Sector>C13</Sector>
      <Composition>7</Composition>
   </GARRISON>
   <GARRISON>
      <!--#18-->
      <!--Calisto-->
      <Sector>C14</Sector>
      <Composition>8</Composition>
   </GARRISON>
   <GARRISON>
      <!--#19-->
      <!--Calisto-->
      <Sector>D13</Sector>
      <Composition>9</Composition>
   </GARRISON>
   <GARRISON>
      <!--#20-->
      <!--Calisto-->
      <Sector>E13</Sector>
      <Composition>8</Composition>
   </GARRISON>
   <GARRISON>
      <!--#21-->
      <!--Galileo-->
      <Sector>F8</Sector>
      <Composition>7</Composition>
   </GARRISON>
   <GARRISON>
      <!--#22-->
      <!--Galileo-->
      <Sector>F9</Sector>
      <Composition>10</Composition>
   </GARRISON>
   <GARRISON>
      <!--#21-->
      <!--Galileo-->
      <Sector>G7</Sector>
      <Composition>7</Composition>
   </GARRISON>
   <GARRISON>
      <!--#22-->
      <!--Galileo-->
      <Sector>G8</Sector>
      <Composition>10</Composition>
   </GARRISON>
   <GARRISON>
      <!--#23-->
      <!--Galileo-->
      <Sector>G9</Sector>
      <Composition>7</Composition>
   </GARRISON>
   <GARRISON>
      <!--#24-->
      <!--Galileo-->
      <Sector>G10</Sector>
      <Composition>8</Composition>
   </GARRISON>
   <GARRISON>
      <!--#25-->
      <!--Galileo-->
      <Sector>H8</Sector>
      <Composition>9</Composition>
   </GARRISON>
   <GARRISON>
      <!--#26-->
      <!--Arms Depot W Galileo-->
      <Sector>F6</Sector>
      <Composition>6</Composition>
   </GARRISON>
   <GARRISON>
      <!--#27-->
      <!--Drake-->
      <Sector>G1</Sector>
      <Composition>7</Composition>
   </GARRISON>
   <GARRISON>
      <!--#28-->
      <!--Drake-->
      <Sector>G2</Sector>
      <Composition>7</Composition>
   </GARRISON>
   <GARRISON>
      <!--#29-->
      <!--Drake-->
      <Sector>G3</Sector>
      <Composition>8</Composition>
   </GARRISON>
   <GARRISON>
      <!--#30-->
      <!--Drake-->
      <Sector>H1</Sector>
      <Composition>7</Composition>
   </GARRISON>
   <GARRISON>
      <!--#31-->
      <!--Drake-->
      <Sector>H2</Sector>
      <Composition>7</Composition>
   </GARRISON>
   <GARRISON>
      <!--#32-->
      <!--Drake-->
      <Sector>H3</Sector>
      <Composition>9</Composition>
   </GARRISON>
   <GARRISON>
      <!--#33-->
      <!--Drake-->
      <Sector>I1</Sector>
      <Composition>8</Composition>
   </GARRISON>
   <GARRISON>
      <!--#34-->
      <!--Drake-->
      <Sector>I2</Sector>
      <Composition>8</Composition>
   </GARRISON>
   <GARRISON>
      <!--#35-->
      <!--Drake-->
      <Sector>I3</Sector>
      <Composition>1</Composition>
   </GARRISON>
   <GARRISON>
      <!--#36-->
      <!--Gotham-->
      <Sector>H6</Sector>
      <Composition>8</Composition>
   </GARRISON>
   <GARRISON>
      <!--#37-->
      <!--Gotham-->
      <Sector>I6</Sector>
      <Composition>7</Composition>
   </GARRISON>
   <GARRISON>
      <!--#38-->
      <!--Gotham-->
      <Sector>J6</Sector>
      <Composition>8</Composition>
   </GARRISON>
   <GARRISON>
      <!--#39-->
      <!--Troy-->
      <Sector>H12</Sector>
      <Composition>8</Composition>
   </GARRISON>
   <GARRISON>
      <!--#40-->
      <!--Troy-->
      <Sector>H13</Sector>
      <Composition>7</Composition>
   </GARRISON>
   <GARRISON>
      <!--#41-->
      <!--Troy-->
      <Sector>H14</Sector>
      <Composition>9</Composition>
   </GARRISON>
   <GARRISON>
      <!--#42-->
      <!--Troy-->
      <Sector>I13</Sector>
      <Composition>6</Composition>
   </GARRISON>
   <GARRISON>
      <!--#43-->
      <!--Troy-->
      <Sector>I14</Sector>
      <Composition>9</Composition>
   </GARRISON>
   <GARRISON>
      <!--#44-->
      <!--Prax-->
      <Sector>J4</Sector>
      <Composition>9</Composition>
   </GARRISON>
   <GARRISON>
      <!--#45-->
      <!--Prax-->
      <Sector>K4</Sector>
      <Composition>9</Composition>
   </GARRISON>
   <GARRISON>
      <!--#46-->
      <!--Tixa-->
      <Sector>J9</Sector>
      <Composition>9</Composition>
   </GARRISON>
   <GARRISON>
      <!--#47-->
      <!--Balime-->
      <Sector>K12</Sector>
      <Composition>8</Composition>
   </GARRISON>
   <GARRISON>
      <!--#48-->
      <!--Balime-->
      <Sector>K13</Sector>
      <Composition>8</Composition>
   </GARRISON>
   <GARRISON>
      <!--#49-->
      <!--Balime-->
      <Sector>L12</Sector>
      <Composition>9</Composition>
   </GARRISON>
   <GARRISON>
      <!--#50-->
      <!--Balime-->
      <Sector>L13</Sector>
      <Composition>7</Composition>
   </GARRISON>
   <GARRISON>
      <!--#51-->
      <!--Adrian-->
      <Sector>N2</Sector>
      <Composition>1</Composition>
   </GARRISON>
   <GARRISON>
      <!--#52-->
      <!--Adrian-->
      <Sector>N3</Sector>
      <Composition>1</Composition>
   </GARRISON>
   <GARRISON>
      <!--#53-->
      <!--Adrian-->
      <Sector>N4</Sector>
      <Composition>2</Composition>
   </GARRISON>
   <GARRISON>
      <!--#54-->
      <!--Adrian-->
      <Sector>N5</Sector>
      <Composition>1</Composition>
   </GARRISON>
   <GARRISON>
      <!--#55-->
      <!--Adrian-->
      <Sector>O2</Sector>
      <Composition>1</Composition>
   </GARRISON>
   <GARRISON>
      <!--#56-->
      <!--Adrian-->
      <Sector>O3</Sector>
      <Composition>1</Composition>
   </GARRISON>
   <GARRISON>
      <!--#57-->
      <!--Adrian-->
      <Sector>O4</Sector>
      <Composition>1</Composition>
   </GARRISON>
   <GARRISON>
      <!--#58-->
      <!--Adrian-->
      <Sector>O5</Sector>
      <Composition>1</Composition>
   </GARRISON>
   <GARRISON>
      <!--#59-->
      <!--Adrian-->
      <Sector>P2</Sector>
      <Composition>1</Composition>
   </GARRISON>
   <GARRISON>
      <!--#60-->
      <!--Adrian-->
      <Sector>P3</Sector>
      <Composition>0</Composition>
   </GARRISON>
   <GARRISON>
      <!--#61-->
      <!--Adrian-->
      <Sector>P4</Sector>
      <Composition>1</Composition>
   </GARRISON>
   <GARRISON>
      <!--#62-->
      <!--Adrian-->
      <Sector>P5</Sector>
      <Composition>7</Composition>
   </GARRISON>
   <GARRISON>
      <!--#63-->
      <!--Island-->
      <Sector>N12</Sector>
      <Composition>7</Composition>
   </GARRISON>
   <GARRISON>
      <!--#64-->
      <!--Island-->
      <Sector>O11</Sector>
      <Composition>7</Composition>
   </GARRISON>
   <GARRISON>
      <!--#65-->
      <!--Outpost L3-->
      <Sector>L3</Sector>
      <Composition>7</Composition>
   </GARRISON>
   <GARRISON>
      <!--#66-->
      <!--Island-->
      <Sector>O13</Sector>
      <Composition>7</Composition>
   </GARRISON>
   <GARRISON>
      <!--#67-->
      <!--Island-->
      <Sector>P9</Sector>
      <Composition>7</Composition>
   </GARRISON>
   <GARRISON>
      <!--#68-->
      <!--Island-->
      <Sector>P10</Sector>
      <Composition>7</Composition>
   </GARRISON>
   <GARRISON>
      <!--#69-->
      <!--Island-->
      <Sector>P11</Sector>
      <Composition>7</Composition>
   </GARRISON>
   <GARRISON>
      <!--#70-->
      <!--Island-->
      <Sector>P12</Sector>
      <Composition>7</Composition>
   </GARRISON>
   <GARRISON>
      <!--#71-->
      <!--Island-->
      <Sector>P13</Sector>
      <Composition>7</Composition>
   </GARRISON>
   <GARRISON>
      <!--#72-->
      <!--NW SAM-->
      <Sector>D2</Sector>
      <Composition>11</Composition>
   </GARRISON>
   <GARRISON>
      <!--#73-->
      <!--NE SAM-->
      <Sector>D15</Sector>
      <Composition>11</Composition>
   </GARRISON>
   <GARRISON>
      <!--#74-->
      <!--Central SAM-->
      <Sector>I8</Sector>
      <Composition>11</Composition>
   </GARRISON>
   <GARRISON>
      <!--#75-->
      <!--Gun Runners Sheraton-->
      <Sector>D1</Sector>
      <Composition>6</Composition>
   </GARRISON>
   <GARRISON>
      <!--#76-->
      <!--Gun Runners Calisto-->
      <Sector>E12</Sector>
      <Composition>6</Composition>
   </GARRISON>
   <GARRISON>
      <!--#77-->
      <!--Gun Runners Drake-->
      <Sector>I5</Sector>
      <Composition>6</Composition>
   </GARRISON>
   <GARRISON>
      <!--#78-->
      <!--Gun Runners Troy-->
      <Sector>I16</Sector>
      <Composition>6</Composition>
   </GARRISON>
   <GARRISON>
      <!--#79-->
      <!--Gun Runners Airstrip-->
      <Sector>M14</Sector>
      <Composition>6</Composition>
   </GARRISON>
   <GARRISON>
      <!--#80-->
      <!--Military Base-->
      <Sector>L8</Sector>
      <Composition>11</Composition>
   </GARRISON>
   <GARRISON>
      <!--#81-->
      <!--Adrian Blockade-->
      <Sector>M2</Sector>
      <Composition>3</Composition>
   </GARRISON>
   <GARRISON>
      <!--#82-->
      <!--Adrian Blockade-->
      <Sector>M3</Sector>
      <Composition>3</Composition>
   </GARRISON>
   <GARRISON>
      <!--#83-->
      <!--Adrian Blockade-->
      <Sector>M4</Sector>
      <Composition>3</Composition>
   </GARRISON>
   <GARRISON>
      <!--#84-->
      <!--Adrian Blockade-->
      <Sector>M5</Sector>
      <Composition>3</Composition>
   </GARRISON>
   <GARRISON>
      <!--#85-->
      <!--Adrian Blockade-->
      <Sector>N6</Sector>
      <Composition>3</Composition>
   </GARRISON>
   <GARRISON>
      <!--#86-->
      <!--Adrian Blockade-->
      <Sector>N7</Sector>
      <Composition>4</Composition>
   </GARRISON>
   <GARRISON>
      <!--#87-->
      <!--Adrian Blockade-->
      <Sector>O6</Sector>
      <Composition>3</Composition>
   </GARRISON>
   <GARRISON>
      <!--#88-->
      <!--Adrian Blockade-->
      <Sector>P6</Sector>
      <Composition>0</Composition>
   </GARRISON>
   <GARRISON>
      <!--#89-->
      <!--Entrance-->
      <Sector>P7</Sector>
      <Composition>0</Composition>
   </GARRISON>
   <GARRISON>
      <!--#90-->
      <!--Power Station-->
      <Sector>C9</Sector>
      <Composition>7</Composition>
   </GARRISON>
   <GARRISON>
      <!--#91-->
      <!--Casino-->
      <Sector>D9</Sector>
      <Composition>7</Composition>
   </GARRISON>
   <GARRISON>
      <!--#91-->
      <!--Naval Station-->
      <Sector>L1</Sector>
      <Composition>11</Composition>
   </GARRISON>
   <GARRISON>
      <!--#92-->
      <!--Harbour-->
      <Sector>M11</Sector>
      <Composition>8</Composition>
   </GARRISON>
   <GARRISON>
      <!--#93-->
      <!--Harbour-->
      <Sector>M13</Sector>
      <Composition>8</Composition>
   </GARRISON>
   <GARRISON>
      <!--#94-->
      <!--Harbour-->
      <Sector>C11</Sector>
      <Composition>8</Composition>
   </GARRISON>
   <GARRISON>
      <!--#95-->
      <!--Hydro Dam-->
      <Sector>B4</Sector>
      <Composition>8</Composition>
   </GARRISON>
   <GARRISON>
      <!--#96-->
      <!--Sheraton Roadblock-->
      <Sector>C2</Sector>
      <Composition>8</Composition>
   </GARRISON>
   <GARRISON>
      <!--#97-->
      <!--GR Airfield-->
      <Sector>L14</Sector>
      <Composition>9</Composition>
   </GARRISON>
   <GARRISON>
      <!--#98-->
      <!--Bridge into Galileo-->
      <Sector>E9</Sector>
      <Composition>10</Composition>
   </GARRISON>
   <GARRISON>
      <!--#99-->
      <!--Naval Station-->
      <Sector>P7</Sector>
      <Composition>11</Composition>
   </GARRISON>
</GARRISON_INFO>